{
    "Name": "Paddy Taro",
    "Product": "Paddy Taro Root",
    "SeedName": "Paddy Taro Seeds",
    "SeedDescription": "Plant these in fall. Takes 14 days to mature.",
    "Type": "Vegetable",
    "CropType": "Paddy",

    "Seasons": ["fall"],
    "Phases": [3, 4, 4, 3, ],
    "RegrowthPhase": -1,
    "HarvestWithScythe": true,
    "TrellisCrop": false,
    "Colors": null,
    "Bonus":
    {
        "MinimumPerHarvest": 1,
        "MaximumPerHarvest": 1,
        "MaxIncreasePerFarmLevel": 5,
        "ExtraChance": 0.0,
    },
    "SeedPurchaseFrom": "Sandy",
    "SeedPurchasePrice": 320,
    "SeedPurchaseRequirements": [
        "y 2",
    ],

    "SeedNameLocalization":
    {
         // "es": "",
        "ko": "토란 씨앗",
        "de": "Taroknollen-Saat",
         // "fr": "",
         // "hu": "",
         // "it": "",
        "ja": "タロイモの種芋",
        "pt": "Sementes de Taro",
        "ru": "Семена таро",
         // "tr": "",
          "zh": "芋头种子",
    },
    "SeedDescriptionLocalization":
    {
         // "es": "",
        "ko": "가을 작물. 성장하려면 14일이 소요됩니다.",
        "de": "Pflanze sie im Herbst. Wächst in 14 Tagen heran.",
         // "fr": "",
         // "hu": "",
         // "it": "",
        "ja": "秋植えの作物。そだつのに14日かかる。",
        "pt": "Plante-as no outono. Leva 14 dias para amadurecer",
        "ru": "Сажайте осенью. Вырастает через 14 дней.",
         // "tr": "",
          "zh": "秋天播种，14天成熟。",
    }
}