{
    "Name": "Cooked Beast Meat",
    "Description": "Meat from a wild beast, already cooked and ready to be used in recipes.",
    "Category": "Cooking",
    "Edibility": 60,
    "Price": 225,
    "IsColored": false,
    "GiftTastes":
    {
        "Dislike": ["Abigail", "Alex", "Caroline", "Clint", "Demetrius", "Dwarf", "Elliott", "Emily", "Evelyn", "George", "Gus", "Haley", "Harvey", "Jas", "Jodi", "Kent", "Krobus", "Leah", "Lewis", "Linus", "Marnie", "Maru", "Pam", "Penny", "Pierre", "Robin", "Sam", "Sandy", "Shane", "Vincent", "Willy", "Wizard"],
        "Hate": ["Sebastian"],
    },
    "Recipe":
    {
        "ResultCount": 1,
        "Ingredients": [
        {
            "Object": "Beast Meat",
            "Count": 1,
        },
        {
            "Object": "Seasonings",
            "Count": 1,
        }, ],
        "IsDefault": true,
    },
    "CanPurchase": true,
    "PurchaseFrom": "Gus",
    "PurchasePrice": 310,
    "PurchaseRequirements": null,
    "NameLocalization":
    {
        "es": "Carne de bestia cocinada",
        "ko": "구운 야생고기.",
        // "de": "",
        "fr": "Viande de bête cuite",
        "hu": "Sült vadhús",
        // "it": "",
        // "ja": "",
        // "pt": "",
        // "ru": "",
        // "tr": "",
         "zh": "熟制野兽肉",
    },
    "DescriptionLocalization":
    {
        "es": "Carne de bestia salvaje, ya cocinada y lista para ser utilizada en recetas.",
        "ko": "야생짐승의 고기. 완전히 구워져서 조리될 준비가 되었습니다.",
        // "de": "",
        "fr": "De la viande d'une bête sauvage, déjà cuite et prête à être utilisée dans des recettes.",
        "hu": "Egy vadállat húsából készített steak, megsütve, felhasználásra készen.",
        // "it": "",
        // "ja": "",
        // "pt": "",
        // "ru": "",
        // "tr": "",
         "zh": "来自野生动物的肉，已经煮熟，准备用于烹调。",
    },
    "ContextTags": [
        "cooked_meat",
        "meat_item",
    ],    
    "DisableWithMod": "HadiZosa.BFAVnewmeat"
}
