{
    "Name": "Kidney Bean",
    "Description": "They contain a high amount of phytohemagglutinin which makes them more toxic than other beans.",
    "Category": "Vegetable",
    "Edibility": 12,
    "Price": 35,
    "IsColored": false,
    "Recipe": null,
    "GiftTastes":
    {
        "Love": ["Krobus"],
        "Hate": ["Alex", "Caroline", "Clint", "Demetrius", "Dwarf", "Elliott", "Emily", "Evelyn", "George", "Gus", "Jodi", "Kent", "Harvey", "Leah", "Linus", "Marnie", "Maru", "Pam", "Penny", "Pierre", "Robin", "Sandy", "Shane", "Willy", "Wizard", "Abigail", "Haley", "Jas", "Sam", "Sebastian", "Vincent", "Lewis"],
    },
    "NameLocalization":
    {
         // "es": "",
         // "ko": "",
         // "de": "",
         // "fr": "",
         // "hu": "",
         // "it": "",
         // "ja": "",
         // "pt": "",
         // "ru": "",
         // "tr": "",
         // "zh": "",
    },
    "DescriptionLocalization":
    {
         // "es": "",
         // "ko": "",
         // "de": "",
         // "fr": "",
         // "hu": "",
         // "it": "",
         // "ja": "",
         // "pt": "",
         // "ru": "",
         // "tr": "",
         // "zh": "",
    }
}