{
	"name": "Farmer to Florist Machines Redux",
	"author": "Kildarien (original); SpringsSong (port)",
	"version": "1.0.1",
	"machines":
	[
		{
			"id": 0,
			"name": "Dryer",
			"description": "Used to dry flowers and leaves for tea making, and vegetables into chips.",
			"category": "Crafting",
			"texture": "drying rack.png",
			"crafting": "709 30 771 20 334 1",
			"pulsate": true,
			"readyindex": 2,
			"tileindex": 0,
			"frames": 1,
			"production":
			[
				{
					"item": "Tea Bag",
					"prefix": true,
					"time": 2000,
					"quality": -1,
					"price": "original + (input * 2)",
					"materials":
					[
						{
							"index": -80
						}
					]
				},
				{	
					"name": "Chips",
					"item": "Veggie Chips",
					"prefix": true,
					"time": 2000,
					"quality": -1,
					"price": "original + (input * 1.35)",
					"materials":
					[
						{
							"index": -75
						}
					]
				},
				{
					"name": "Dried",
					"item": "Dried Poison",
					"suffix": true,
					"time": 2000,
					"quality": -1,					
					"price": "original + (input * 1.85)",
					"materials":
					[
						{
							"index": 18
						}
					]
				},
				{
					"name": "Dried",
					"item": "Dried Poison",
					"suffix": true,
					"time": 2000,
					"quality": -1,					
					"price": "original + (input * 1.85)",
					"materials":
					[
						{
							"index": 402
						}
					]
				},
				{
					"name": "Dried",
					"item": "Dried Poison",
					"suffix": true,
					"time": 2000,
					"quality": -1,
					"price": "original + (input * 1.85)",
					"materials":
					[
						{
							"name": "Clematis"
						}
					]
				},
				{
					"name": "Dried",
					"item": "Dried Poison",
					"suffix": true,
					"time": 2000,
					"quality": -1,
					"price": "original + (input * 1.85)",
					"materials":
					[
						{
							"name": "Wisteria"
						}
					]
				},
				{
					"name": "Dried",
					"item": "Dried Poison",
					"suffix": true,
					"time": 2000,
					"quality": -1,
					"price": "original + (input * 1.85)",
					"materials":
					[
						{
							"name": "Iris"
						}
					]
				},
				{
					"name": "Dried",
					"item": "Dried Poison",
					"suffix": true,
					"time": 2000,
					"quality": -1,
					"price": "original + (input * 1.85)",
					"materials":
					[
						{
							"name": "Delphinium"
						}
					]
				},
				{
					"name": "Dried",
					"item": "Dried Poison",
					"suffix": true,
					"time": 2000,
					"quality": -1,
					"price": "original + (input * 1.85)",
					"materials":
					[
						{
							"name": "Hyacinth"
						}
					]
				},
				{
					"name": "Dried",
					"item": "Dried Poison",
					"suffix": true,
					"time": 2000,
					"quality": -1,
					"price": "original + (input * 1.85)",
					"materials":
					[
						{
							"name": "Hydrangea"
						}
					]
				}
			]
		},
		{
			"id": 1,
			"name": "Perfumery",
			"description": "Processes flowers to make perfume.",
			"category": "Crafting",
			"texture": "perfumery.png",
			"crafting": "766 40 709 20 335 1",
			"pulsate": true,
			"tileindex": 0,
			"production":
			[
				{
					"item": "Perfume",
					"prefix": true,
					"time": 4000,
					"quality": -1,
					"price": "original + (input * 2.25)",
					"materials":
					[
						{
							"index": -80
						}
					]
				}
			]
		},
		{
			"id": 2,
			"name": "Soap Maker",
			"description": "Combines flowers and oil into a bar of soap.",
			"texture": "soap maker.png",
			"crafting": "709 20 382 5 336 1",
			"pulsate": true,
			"tileindex": 0,
			"starter": 
			{
				"index": 247 
			},
			"production":
			[
				{
					"name": "Soap",
					"item": "Floral Soap",
					"prefix": true,
					"time": 6000,
					"quality": -1,
					"price": "original + (input * 1.45)",
					"materials":
					[
						{
							"index": -80
						}
					]
				},
				{
					"name": "Soap",
					"item": "Fruity Soap",
					"prefix": true,
					"time": 6000,
					"quality": -1,
					"price": "original + (input * 1.45)",
					"materials":
					[
						{
							"index": -79
						}
					]
				}
			]
		}
	]
}