{
    "Name": "Asam Pedas",
    "Description": "A dish with a distinctive sour and spicy flavor. Prepared with fish, tomatoes, and seasonings.",
    "Category": "Cooking",
    "Edibility": 80,
    "EdibleIsDrink": false,
    "EdibleBuffs": null,
    "Price": 675,
    "IsColored": false,
    "GiftTastes":
    {
        "Love": ["Gus", "Shane"],
        "Like": ["Willy", "Sam", "Penny", "Maru", "Haley", "Caroline", "Elliott", "Krobus", "Linus", "Jodi", "Pierre", "Clint"],
        "Dislike": ["Sebastian", "Marnie", "Harvey", ],
    },
    "Recipe":
    {
        "ResultCount": 1,
        "Ingredients": [
        {
            "Object": -4,
            "Count": 1,
        },
        {
            "Object": 256,
            "Count": 1,
        },
        {
            "Object": "Seasonings",
            "Count": 1,
        },
        {
            "Object": "Broth",
            "Count": 1,
        }, ],
        "CanPurchase": true,
        "PurchaseFrom": "Gus",
        "PurchasePrice": 1850,
        "PurchaseRequirements": ["y 4"],
    },
    "EnableWithMod": "ppja.evenmorerecipes",
    "NameLocalization":
    {
        // "es": "",
        // "ko": "",
        // "de": "",
        "fr": "Asam Pedas",
        // "hu": "",
        // "it": "",
        "ja": "アッサムペダス",
        "pt": "Asam Pedas",
        "ru": "Бульон кисло-пряный",
        "tr": "Asam Pedas",
        // "zh": "",
    },
    "DescriptionLocalization":
    {
        // "es": "",
        // "ko": "",
        // "de": "",
        "fr": "Un plat à la saveur acide et relevée distinctive. Préparé avec du poisson, des tomates et des épices.",
        // "hu": "",
        // "it": "",
        "ja": "酸味と辛さの利いた美味しい料理。材料は魚とトマトと調味料。",
        "pt": "Um prato com um sabor azedo e picante distinto. Preparado com peixes, tomates e temperos.",
        "ru": "Блюдо с характерным кисло - пряным вкусом. Готовится с рыбой, помидорами и приправами",
        "tr": "Ayýrt edici acýlý ve ekþi bir tadý var. Balýk,domates ve baharatlarla hazýrlanýr.",
        // "zh": "",
    }
}