{
  "Name": "Bouquet of Exuberance",
  "Description": "A bouquet of brilliantly-colored flowers. It seems to be radiating energy.",
  "Category": "Crafting",
  "Edibility": -300,
  "Price": 1250,
  "IsColored": false,
  "Recipe": {
	  "ResultCount": 1,
	  "Ingredients": [
		  {
			  "Object": "Hibiscus",
			  "Count": 1
		  },
		  {
			  "Object": 591,
			  "Count": 1
		  },
		  {
			  "Object": 376,
			  "Count": 1,
		  },
		  {
			  "Object": "Herbal Peony",
			  "Count": 1
		  }
	  ],
	  "CanPurchase": true,
	  "PurchaseFrom": "Robin",
	  "PurchasePrice": 750,
	  "PurchaseRequirements": null,
  },
"GiftTastes":
{
"Love": ["Harvey", "Emily"],
"Like": ["Leah", "Abigail", "Elliott", "Penny", "Maru", "Shane", "Alex", "Sam", "Sebastian", "Haley"],
"Neutral": ["Linus", "Wizard", "Gus", "Willy", "Dwarf", "Krobus", "Sandy"],
"Dislike": ["Demetrius", "Evelyn", "Caroline", "Kent", "Lewis", "Marnie", "Robin", "Pam", "Pierre", "Jas", "Vincent"],
"Hate": ["George", "Clint", "Jodi"]
},
}