{
    "Name": "Meaty Burrito Wrap",
    "Description": "So juicy, so tender! A completely different experience from regular beef burritos.",
    "Category": "Cooking",
    "Edibility": 60,
    "Price": 725,
    "IsColored": false,
    "Recipe":
    {
        "ResultCount": 1,
        "Ingredients": [
        {
            "Object": "Cooked Alpaca Meat",
            "Count": 1,
        },
        {
            "Object": 229,
            "Count": 1,
        },
        {
            "Object": 256,
            "Count": 1,
        },
        {
            "Object": 424,
            "Count": 1,
        }, ],
        "CanPurchase": true,
        "PurchaseFrom": "Gus",
        "PurchasePrice": 725,
        "PurchaseRequirements": ["HasCookingRecipe Tortilla", "y 4"],
    },

    "NameLocalization":
    {
        "es": "Burrito con carne",
        "ko": "고기듬뿍 부리또 말이",
        // "de": "",
        "fr": "Burrito wrap plein de viande",
        "hu": "Húsos burrito wrap",
        // "it": "",
        // "ja": "",
        // "pt": "",
        // "ru": "",
        // "tr": "",
        "zh": "多肉墨西哥卷饼",
    },
    "DescriptionLocalization":
    {
        "es": "¡Tan jugoso, tan tierno! Una experiencia completamente diferente a los burritos de ternera normales.",
        "ko": "육즙이 넘치고 너무 부드러워! 일반 소고기 부리또와는 차원이 달라.",
        // "de": "",
        "fr": "Si juteux, si tendre ! Une expérience complétement différente des burritos au bœuf classiques.",
        "hu": "Olyan lédús, olyan lágy! Fogyasztása egy teljesen új élmény a többi húsos burrítóhoz képest.",
        // "it": "",
        // "ja": "",
        // "pt": "",
        // "ru": "",
        // "tr": "",
        "zh": "如此多汁，如此柔软！和普通的牛肉墨西哥卷饼完全不同的体验。",
    },
    "DisableWithMod": "HadiZosa.BFAVnewmeat"
}