{
    "Name": "Green Ribbon",
    "Description": "A subtle strain that lends itself to an earthy taste. You can use it to create Fruit Pebbles OG.",
    "Category": "Flower",
    "CategoryTextOverride": "Hybrid",
    "Edibility": 18,
    "Price": 600,
    "IsColored": false,
    "Recipe": null,
    "GiftTastes":
    {
        "Love": ["Sebastian", "Sam", "Abigail"],
        "Neutral": ["Robin", "Demetrius", "Pierre", "Penny", "Pam", "Kent", "Elliott", "Harvey", "Willy", "Lewis", "Clint"],
        "Hate": ["Jas", "Vincent"],
    },
    "NameLocalization":
    {
         // "es": "",
         // "ko": "",
         // "de": "",
        "fr": "Green Ribbon",
         "hu": "Green Ribbon",
         // "it": "",
         // "ja": "",
         // "pt": "",
         // "ru": "",
         // "tr": "",
         // "zh": "",
    },
    "DescriptionLocalization":
    {
         // "es": "",
         // "ko": "",
         // "de": "",
        "fr": "Une souche subtile à qui l'on prête un goût terreux. On peut s'en servir pour créer une Fruit Pebbles OG.",
         "hu": "Egy kifinomult fajta, mely íze egy kicsit földes. Fruit Pebbles OG-t tudsz belőle készíteni.",
         // "it": "",
         // "ja": "",
         // "pt": "",
         // "ru": "",
         // "tr": "",
         // "zh": "",
    },
    "ContextTags": [
        "flower_item",
        "flower_cannabinoid",
        "trellis_item"
    ]
}
