{
    "Name": "Potted Summer Spangle",
    "Description": "A summer spangle potted in a little wooden pot. Make sure to water it!",
    "Price": 1,
    "ProvidesLight": false,
    "Recipe":
    {
        "ResultCount": 1,
        "Ingredients": [
        {
            "Object": 593,
            "Count": 1,
        },
        {
            "Object": 388,
            "Count": 10,
        },
        {
            "Object": 330,
            "Count": 10,
        }, ],
        "CanPurchase": false,
    },
    "NameLocalization":
    {
        "es": "Lentejuela de verano en maceta",
        "ko": "실내 화초 여름 별꽃",
        "de": "Eingemachter Sommer Spangle",
        //"fr": "",
        "hu": "Cserepes Nyári tölgyfagubacs",
        //"it": "",
        "ja": "サマースパングルの鉢植え",
        "pt": "Vaso de Miçanga",
        "ru": "Летний блестник в горшке",
        //"tr": "",
        "zh": "夏日亮片盆栽",
    },
    "DescriptionLocalization":
    {
        "es": "Una lentejuela veraniega en una pequeña maceta de madera. ¡Asegúrate de regarlo!",
        "ko": "작은 나무 화분에 심겨진 여름 별꽃 입니다. 물 주는거 잊지마세요!",
        "de": "Ein Sommerflitter in einem kleinen Holztopf. Achten Sie darauf, es zu gießen!",
        //"fr": "",
        "hu": "Egy nyári tölgyfagubacs cserépben. Ne felejtsd el megöntözni!",
        //"it": "",
        "ja": "サマースパングルが植えられた木製の小さな鉢。水やりを忘れずに。",
        "pt": "Uma miçanga em um pequeno vaso de madeira. Lembre-se sempre de regá-la!",
        "ru": "Летний блестник в маленьком деревянном горшочке. Не забывайте поливать!",
        //"tr": "",
        "zh": "一个小木盆里的夏日亮片。记得给它浇水！",
    }
}
