{
    "Name": "Hyacinth",
    "Description": "It blooms early in the spring with incredibly fragrant flowers.",
    "Category": "Flower",
    "Edibility": -30,
    "Price": 60,
    "IsColored": true,
    "Recipe": null,
    "NameLocalization":
    {
        "es": "Jacinto",
        "ko": "히아신스",
        "de": "Hyazinthe",
        "fr": "Jacinthe",
        "hu": "Jácint",
        "it": "Giacinto",
        "ja": "ヒヤシンス",
        "pt": "Jacinto",
        "ru": "Гиацинт",
        "tr": "Sümbül",
        "zh": "风信子",
    },
    "DescriptionLocalization":
    {
        "es": "Florece a principios de la primavera con flores increíblemente fragantes.",
        "ko": "봄에는 믿을 수 없을 정도로 향기로운 꽃들이 피어난다.",
        "de": "Es blüht früh im Frühjahr mit unglaublich duftenden Blüten.",
        "fr": "Il fleurit au début du printemps avec des fleurs incroyablement parfumées.",
        "hu": "Kora tavasszal hoz virágot, melyek hihetetlenül illatosak.",
        "it": "Fiorisce all'inizio della primavera con fiori incredibilmente profumati.",
        "ja": "それは非常に香り高い花で春の初めに咲きます。",
        "pt": "Floresce no início da primavera com flores incrivelmente perfumadas.",
        "ru": "Цветет рано весной невероятно ароматными цветами.",
        "tr": "İnanılmaz kokulu çiçekleri ile ilkbaharda erken çiçek açar.",
        "zh": "在早春开放，花朵芳香扑鼻。",
    },
    "ContextTags": [
        "flower_poisonous",
        "flower_item",
        "color_blue",
        "season_spring"
    ]
}