{
    "Name": "Lychee",
    "Description": "The outside is roughly textured and inedible, but the inside is sweet.",
    "Category": "Fruit",
    "Edibility": 12,
    "Price": 110,
    "IsColored": false,
    "GiftTastes":
    {
        "Love": ["Sandy", "Haley", "Jodi"],
        "Like": ["Krobus", "Evelyn", "Elliott"],
        "Neutral": ["Alex", "Caroline", "Clint", "Demetrius", "Dwarf", "Emily", "George", "Gus", "Harvey", "Kent", "Leah", "Lewis", "Linus", "Marnie", "Maru", "Pam", "Penny", "Pierre", "Robin", "Sam", "Sebastian", "Shane", "Willy", "Wizard", "Abigail", "Jas", "Vincent"],
    },
    "NameLocalization":
    {
        "es": "Lichi",
        "ko": "리치",
        "de": "Litschi",
        "fr": "Litchi",
        "hu": "Licsi",
        // "it": "",
        "ja": "ライチ",
         "pt": "Lichia",
        "ru": "Личи",
        // "tr": "",
        "zh": "荔枝",
    },
    "DescriptionLocalization":
    {
        "es": "La exterior es aspera de textura y incomible, pero el interior es dulce",
        "ko": "겉은 질감이 거칠고 먹을 수 없지만, 안은 달콤합니다.",
        "de": "Die Schale ist rau und nicht essbar, aber das Innere ist süß.",
        "fr": "L'enveloppe est écailleuse et non comestible, mais l'intérieur est sucré.",
        "hu": "A gyümölcs külseje ráncos és ehetetlen, de a belseje édes.",
        // "it": "",
        "ja": "皮はざらざらしていて食べられないが、内側の実は甘い。",
         "pt": "O exterior é aproximadamente texturizado e não comestível, mas o interior é doce.",
        "ru": "Кожица грубая и не съедобная, но внутри плод сладкий.",
        // "tr": "",
        "zh": "果皮粗糙，不能吃，但果肉很甜。",
    },
    "ContextTags": [
        "season_summer",
        "crop_year_two",
        "fruit_tree_year_two",
        "color_dark_pink",
        "fruit_tree_item",
        "fruit_item",
        "dye_strong"
    ]
}
