{
    "Name": "Cooked Beef",
    "Description": "A thick, juicy slab of beef already cooked and ready to be used in recipes.",
    "Category": "Cooking",
    "Edibility": 60,
    "Price": 175,
    "IsColored": false,
    "GiftTastes":
    {
        "Dislike": ["Abigail", "Alex", "Caroline", "Clint", "Demetrius", "Dwarf", "Elliott", "Emily", "Evelyn", "George", "Gus", "Haley", "Harvey", "Jas", "Jodi", "Kent", "Krobus", "Leah", "Lewis", "Linus", "Marnie", "Maru", "Pam", "Penny", "Pierre", "Robin", "Sam", "Sandy", "Shane", "Vincent", "Willy", "Wizard"],
        "Hate": ["Sebastian"],
    },
    "Recipe":
    {
        "ResultCount": 1,
        "Ingredients": [
        {
            "Object": "Beef",
            "Count": 1,
        },
        {
            "Object": "Ginger",
            "Count": 1,
        },
        {
            "Object": 247,
            "Count": 1,
        },
        {
            "Object": 399,
            "Count": 1,
        }],
        "IsDefault": true,
    },
    "CanPurchase": true,
    "PurchaseFrom": "Gus",
    "PurchasePrice": 175,
    "PurchaseRequirements": null,
    "NameLocalization":
    {
        "es": "",
        "ko": "",
        "de": "",
        "fr": "Boeuf Cuit",
        "hu": "",
        "it": "",
        "ja": "",
        "pt": "",
        "ru": "",
        "tr": "",
        "zh": "熟牛肉",
    },
    "DescriptionLocalization":
    {
        "es": "",
        "ko": "",
        "de": "",
        "fr": "Une plaque de bœuf épaisse et juteuse déjà cuite et prête à être utilisée dans les recettes.",
        "hu": "",
        "it": "",
        "ja": "",
        "pt": "",
        "ru": "",
        "tr": "",
        "zh": "一块又厚又多汁的牛肉，已经煮熟，可以用于烹饪。",
    }
}
